{
    "type": "FeatureCollection",
    "features": [
        {
            "type": "Feature",
            "geometry": {
                "type": "Polygon",
                "coordinates": [
                    [
                        [
                            123.89183,
                            10.48984,
                            0
                        ],
                        [
                            123.890572,
                            10.491,
                            0
                        ],
                        [
                            123.889572,
                            10.49226,
                            0
                        ],
                        [
                            123.888817,
                            10.49343,
                            0
                        ],
                        [
                            123.862747,
                            10.4736,
                            0
                        ],
                        [
                            123.839539,
                            10.45568,
                            0
                        ],
                        [
                            123.837753,
                            10.45392,
                            0
                        ],
                        [
                            123.836823,
                            10.45313,
                            0
                        ],
                        [
                            123.834671,
                            10.45165,
                            0
                        ],
                        [
                            123.832603,
                            10.45018,
                            0
                        ],
                        [
                            123.830544,
                            10.4487,
                            0
                        ],
                        [
                            123.828369,
                            10.4476,
                            0
                        ],
                        [
                            123.82737,
                            10.44656,
                            0
                        ],
                        [
                            123.826981,
                            10.44576,
                            0
                        ],
                        [
                            123.826027,
                            10.44468,
                            0
                        ],
                        [
                            123.824059,
                            10.44369,
                            0
                        ],
                        [
                            123.821426,
                            10.4423,
                            0
                        ],
                        [
                            123.821213,
                            10.44144,
                            0
                        ],
                        [
                            123.820152,
                            10.44145,
                            0
                        ],
                        [
                            123.819443,
                            10.4418,
                            0
                        ],
                        [
                            123.817657,
                            10.44088,
                            0
                        ],
                        [
                            123.816589,
                            10.4401,
                            0
                        ],
                        [
                            123.815247,
                            10.43904,
                            0
                        ],
                        [
                            123.813728,
                            10.43867,
                            0
                        ],
                        [
                            123.812317,
                            10.43741,
                            0
                        ],
                        [
                            123.810677,
                            10.43658,
                            0
                        ],
                        [
                            123.808998,
                            10.43516,
                            0
                        ],
                        [
                            123.808159,
                            10.43333,
                            0
                        ],
                        [
                            123.807602,
                            10.4323,
                            0
                        ],
                        [
                            123.806839,
                            10.43163,
                            0
                        ],
                        [
                            123.806427,
                            10.43094,
                            0
                        ],
                        [
                            123.805878,
                            10.42995,
                            0
                        ],
                        [
                            123.805023,
                            10.42958,
                            0
                        ],
                        [
                            123.803726,
                            10.42801,
                            0
                        ],
                        [
                            123.802612,
                            10.42704,
                            0
                        ],
                        [
                            123.801697,
                            10.42703,
                            0
                        ],
                        [
                            123.800758,
                            10.42719,
                            0
                        ],
                        [
                            123.800819,
                            10.42675,
                            0
                        ],
                        [
                            123.800323,
                            10.42589,
                            0
                        ],
                        [
                            123.799622,
                            10.42484,
                            0
                        ],
                        [
                            123.798782,
                            10.42373,
                            0
                        ],
                        [
                            123.798347,
                            10.42264,
                            0
                        ],
                        [
                            123.798187,
                            10.42219,
                            0
                        ],
                        [
                            123.797729,
                            10.42068,
                            0
                        ],
                        [
                            123.797256,
                            10.41969,
                            0
                        ],
                        [
                            123.797417,
                            10.41877,
                            0
                        ],
                        [
                            123.797607,
                            10.41812,
                            0
                        ],
                        [
                            123.786438,
                            10.40718,
                            0
                        ],
                        [
                            123.774742,
                            10.39587,
                            0
                        ],
                        [
                            123.769737,
                            10.39064,
                            0
                        ],
                        [
                            123.770271,
                            10.38828,
                            0
                        ],
                        [
                            123.770988,
                            10.38565,
                            0
                        ],
                        [
                            123.771538,
                            10.383,
                            0
                        ],
                        [
                            123.771889,
                            10.37922,
                            0
                        ],
                        [
                            123.77195,
                            10.37679,
                            0
                        ],
                        [
                            123.77169,
                            10.37253,
                            0
                        ],
                        [
                            123.771698,
                            10.36923,
                            0
                        ],
                        [
                            123.771744,
                            10.36437,
                            0
                        ],
                        [
                            123.772163,
                            10.36118,
                            0
                        ],
                        [
                            123.772408,
                            10.35608,
                            0
                        ],
                        [
                            123.772926,
                            10.34921,
                            0
                        ],
                        [
                            123.772263,
                            10.34003,
                            0
                        ],
                        [
                            123.771423,
                            10.33322,
                            0
                        ],
                        [
                            123.770569,
                            10.32673,
                            0
                        ],
                        [
                            123.781212,
                            10.32577,
                            0
                        ],
                        [
                            123.782677,
                            10.32555,
                            0
                        ],
                        [
                            123.784637,
                            10.32601,
                            0
                        ],
                        [
                            123.785278,
                            10.32632,
                            0
                        ],
                        [
                            123.788971,
                            10.32772,
                            0
                        ],
                        [
                            123.789787,
                            10.32819,
                            0
                        ],
                        [
                            123.790573,
                            10.32837,
                            0
                        ],
                        [
                            123.79126,
                            10.32845,
                            0
                        ],
                        [
                            123.803467,
                            10.32634,
                            0
                        ],
                        [
                            123.81205,
                            10.32726,
                            0
                        ],
                        [
                            123.812447,
                            10.32691,
                            0
                        ],
                        [
                            123.813179,
                            10.32694,
                            0
                        ],
                        [
                            123.814117,
                            10.32784,
                            0
                        ],
                        [
                            123.814468,
                            10.32823,
                            0
                        ],
                        [
                            123.814949,
                            10.32842,
                            0
                        ],
                        [
                            123.816559,
                            10.32726,
                            0
                        ],
                        [
                            123.817207,
                            10.32692,
                            0
                        ],
                        [
                            123.818024,
                            10.32667,
                            0
                        ],
                        [
                            123.818497,
                            10.32714,
                            0
                        ],
                        [
                            123.81881,
                            10.32779,
                            0
                        ],
                        [
                            123.819023,
                            10.32808,
                            0
                        ],
                        [
                            123.819511,
                            10.32818,
                            0
                        ],
                        [
                            123.820671,
                            10.32717,
                            0
                        ],
                        [
                            123.823486,
                            10.32455,
                            0
                        ],
                        [
                            123.824509,
                            10.32162,
                            0
                        ],
                        [
                            123.824913,
                            10.32014,
                            0
                        ],
                        [
                            123.824059,
                            10.31726,
                            0
                        ],
                        [
                            123.822906,
                            10.31591,
                            0
                        ],
                        [
                            123.822418,
                            10.31416,
                            0
                        ],
                        [
                            123.822403,
                            10.31253,
                            0
                        ],
                        [
                            123.82164,
                            10.31124,
                            0
                        ],
                        [
                            123.820847,
                            10.30975,
                            0
                        ],
                        [
                            123.820297,
                            10.30867,
                            0
                        ],
                        [
                            123.81974,
                            10.30736,
                            0
                        ],
                        [
                            123.828041,
                            10.29654,
                            0
                        ],
                        [
                            123.829674,
                            10.29438,
                            0
                        ],
                        [
                            123.839668,
                            10.28303,
                            0
                        ],
                        [
                            123.841309,
                            10.28054,
                            0
                        ],
                        [
                            123.842979,
                            10.28,
                            0
                        ],
                        [
                            123.843948,
                            10.27923,
                            0
                        ],
                        [
                            123.846413,
                            10.27907,
                            0
                        ],
                        [
                            123.848129,
                            10.27825,
                            0
                        ],
                        [
                            123.849663,
                            10.27677,
                            0
                        ],
                        [
                            123.850578,
                            10.27583,
                            0
                        ],
                        [
                            123.851196,
                            10.27486,
                            0
                        ],
                        [
                            123.851807,
                            10.27386,
                            0
                        ],
                        [
                            123.852547,
                            10.2719,
                            0
                        ],
                        [
                            123.852821,
                            10.27056,
                            0
                        ],
                        [
                            123.853088,
                            10.26982,
                            0
                        ],
                        [
                            123.853394,
                            10.2694,
                            0
                        ],
                        [
                            123.857391,
                            10.26655,
                            0
                        ],
                        [
                            123.861862,
                            10.26393,
                            0
                        ],
                        [
                            123.863197,
                            10.26303,
                            0
                        ],
                        [
                            123.864288,
                            10.26256,
                            0
                        ],
                        [
                            123.865707,
                            10.26195,
                            0
                        ],
                        [
                            123.867668,
                            10.26186,
                            0
                        ],
                        [
                            123.872963,
                            10.26206,
                            0
                        ],
                        [
                            123.875618,
                            10.26213,
                            0
                        ],
                        [
                            123.876198,
                            10.26307,
                            0
                        ],
                        [
                            123.876892,
                            10.26376,
                            0
                        ],
                        [
                            123.877449,
                            10.26404,
                            0
                        ],
                        [
                            123.877724,
                            10.26415,
                            0
                        ],
                        [
                            123.8778,
                            10.26418,
                            0
                        ],
                        [
                            123.878082,
                            10.26459,
                            0
                        ],
                        [
                            123.878288,
                            10.26528,
                            0
                        ],
                        [
                            123.878487,
                            10.26584,
                            0
                        ],
                        [
                            123.878853,
                            10.26625,
                            0
                        ],
                        [
                            123.879402,
                            10.26674,
                            0
                        ],
                        [
                            123.879677,
                            10.26722,
                            0
                        ],
                        [
                            123.880028,
                            10.26777,
                            0
                        ],
                        [
                            123.880463,
                            10.26835,
                            0
                        ],
                        [
                            123.881981,
                            10.27047,
                            0
                        ],
                        [
                            123.88205,
                            10.27054,
                            0
                        ],
                        [
                            123.882469,
                            10.27109,
                            0
                        ],
                        [
                            123.882607,
                            10.27144,
                            0
                        ],
                        [
                            123.88282,
                            10.27192,
                            0
                        ],
                        [
                            123.882889,
                            10.27289,
                            0
                        ],
                        [
                            123.882607,
                            10.2731,
                            0
                        ],
                        [
                            123.882401,
                            10.27316,
                            0
                        ],
                        [
                            123.881981,
                            10.27316,
                            0
                        ],
                        [
                            123.881554,
                            10.27333,
                            0
                        ],
                        [
                            123.881287,
                            10.27344,
                            0
                        ],
                        [
                            123.880943,
                            10.27406,
                            0
                        ],
                        [
                            123.880867,
                            10.27482,
                            0
                        ],
                        [
                            123.881081,
                            10.27662,
                            0
                        ],
                        [
                            123.881126,
                            10.27672,
                            0
                        ],
                        [
                            123.881767,
                            10.278,
                            0
                        ],
                        [
                            123.882332,
                            10.27938,
                            0
                        ],
                        [
                            123.883057,
                            10.28083,
                            0
                        ],
                        [
                            123.883148,
                            10.28092,
                            0
                        ],
                        [
                            123.885002,
                            10.28278,
                            0
                        ],
                        [
                            123.885002,
                            10.28306,
                            0
                        ],
                        [
                            123.886948,
                            10.285,
                            0
                        ],
                        [
                            123.887222,
                            10.28528,
                            0
                        ],
                        [
                            123.887939,
                            10.28578,
                            0
                        ],
                        [
                            123.887939,
                            10.2862,
                            0
                        ],
                        [
                            123.887871,
                            10.28654,
                            0
                        ],
                        [
                            123.887733,
                            10.28696,
                            0
                        ],
                        [
                            123.887733,
                            10.28737,
                            0
                        ],
                        [
                            123.887451,
                            10.28792,
                            0
                        ],
                        [
                            123.887306,
                            10.28813,
                            0
                        ],
                        [
                            123.886887,
                            10.28848,
                            0
                        ],
                        [
                            123.88578,
                            10.28869,
                            0
                        ],
                        [
                            123.885147,
                            10.28869,
                            0
                        ],
                        [
                            123.884872,
                            10.28834,
                            0
                        ],
                        [
                            123.884666,
                            10.2882,
                            0
                        ],
                        [
                            123.884666,
                            10.28806,
                            0
                        ],
                        [
                            123.884468,
                            10.288,
                            0
                        ],
                        [
                            123.884247,
                            10.28792,
                            0
                        ],
                        [
                            123.884033,
                            10.2875,
                            0
                        ],
                        [
                            123.883759,
                            10.28758,
                            0
                        ],
                        [
                            123.883713,
                            10.28811,
                            0
                        ],
                        [
                            123.88369,
                            10.28827,
                            0
                        ],
                        [
                            123.883957,
                            10.28869,
                            0
                        ],
                        [
                            123.884247,
                            10.28896,
                            0
                        ],
                        [
                            123.884666,
                            10.28917,
                            0
                        ],
                        [
                            123.885429,
                            10.28958,
                            0
                        ],
                        [
                            123.885887,
                            10.28945,
                            0
                        ],
                        [
                            123.886612,
                            10.28951,
                            0
                        ],
                        [
                            123.88752,
                            10.28931,
                            0
                        ],
                        [
                            123.888077,
                            10.28903,
                            0
                        ],
                        [
                            123.888496,
                            10.28875,
                            0
                        ],
                        [
                            123.888641,
                            10.28862,
                            0
                        ],
                        [
                            123.889397,
                            10.28834,
                            0
                        ],
                        [
                            123.889961,
                            10.28827,
                            0
                        ],
                        [
                            123.890663,
                            10.28827,
                            0
                        ],
                        [
                            123.891151,
                            10.28855,
                            0
                        ],
                        [
                            123.891663,
                            10.28879,
                            0
                        ],
                        [
                            123.891998,
                            10.28891,
                            0
                        ],
                        [
                            123.89225,
                            10.28887,
                            0
                        ],
                        [
                            123.892517,
                            10.289,
                            0
                        ],
                        [
                            123.892807,
                            10.28906,
                            0
                        ],
                        [
                            123.893089,
                            10.28903,
                            0
                        ],
                        [
                            123.893387,
                            10.28895,
                            0
                        ],
                        [
                            123.893723,
                            10.2889,
                            0
                        ],
                        [
                            123.893929,
                            10.28889,
                            0
                        ],
                        [
                            123.894089,
                            10.28889,
                            0
                        ],
                        [
                            123.894447,
                            10.28889,
                            0
                        ],
                        [
                            123.894768,
                            10.28889,
                            0
                        ],
                        [
                            123.895058,
                            10.28889,
                            0
                        ],
                        [
                            123.895317,
                            10.28889,
                            0
                        ],
                        [
                            123.895607,
                            10.28887,
                            0
                        ],
                        [
                            123.895897,
                            10.28877,
                            0
                        ],
                        [
                            123.896156,
                            10.28857,
                            0
                        ],
                        [
                            123.896446,
                            10.28838,
                            0
                        ],
                        [
                            123.896828,
                            10.28833,
                            0
                        ],
                        [
                            123.897293,
                            10.28833,
                            0
                        ],
                        [
                            123.897812,
                            10.28842,
                            0
                        ],
                        [
                            123.898277,
                            10.28879,
                            0
                        ],
                        [
                            123.898567,
                            10.28926,
                            0
                        ],
                        [
                            123.898613,
                            10.28932,
                            0
                        ],
                        [
                            123.898903,
                            10.28982,
                            0
                        ],
                        [
                            123.899193,
                            10.29021,
                            0
                        ],
                        [
                            123.899521,
                            10.2905,
                            0
                        ],
                        [
                            123.899872,
                            10.29071,
                            0
                        ],
                        [
                            123.900269,
                            10.29083,
                            0
                        ],
                        [
                            123.90065,
                            10.29091,
                            0
                        ],
                        [
                            123.901009,
                            10.29091,
                            0
                        ],
                        [
                            123.901382,
                            10.29085,
                            0
                        ],
                        [
                            123.901802,
                            10.29081,
                            0
                        ],
                        [
                            123.902199,
                            10.2907,
                            0
                        ],
                        [
                            123.902763,
                            10.29058,
                            0
                        ],
                        [
                            123.90329,
                            10.29052,
                            0
                        ],
                        [
                            123.903793,
                            10.29039,
                            0
                        ],
                        [
                            123.904266,
                            10.29035,
                            0
                        ],
                        [
                            123.904694,
                            10.29056,
                            0
                        ],
                        [
                            123.905098,
                            10.29076,
                            0
                        ],
                        [
                            123.905548,
                            10.29082,
                            0
                        ],
                        [
                            123.906067,
                            10.29083,
                            0
                        ],
                        [
                            123.906631,
                            10.29088,
                            0
                        ],
                        [
                            123.907066,
                            10.29108,
                            0
                        ],
                        [
                            123.907463,
                            10.29123,
                            0
                        ],
                        [
                            123.907768,
                            10.29137,
                            0
                        ],
                        [
                            123.908058,
                            10.29144,
                            0
                        ],
                        [
                            123.908333,
                            10.29162,
                            0
                        ],
                        [
                            123.908623,
                            10.29169,
                            0
                        ],
                        [
                            123.90889,
                            10.29186,
                            0
                        ],
                        [
                            123.909149,
                            10.29208,
                            0
                        ],
                        [
                            123.909378,
                            10.29239,
                            0
                        ],
                        [
                            123.909576,
                            10.29278,
                            0
                        ],
                        [
                            123.90963,
                            10.29301,
                            0
                        ],
                        [
                            123.90966,
                            10.29313,
                            0
                        ],
                        [
                            123.909843,
                            10.2934,
                            0
                        ],
                        [
                            123.910149,
                            10.2938,
                            0
                        ],
                        [
                            123.910408,
                            10.29416,
                            0
                        ],
                        [
                            123.910606,
                            10.29448,
                            0
                        ],
                        [
                            123.910797,
                            10.29475,
                            0
                        ],
                        [
                            123.910843,
                            10.29501,
                            0
                        ],
                        [
                            123.910851,
                            10.29527,
                            0
                        ],
                        [
                            123.910744,
                            10.29574,
                            0
                        ],
                        [
                            123.910873,
                            10.29593,
                            0
                        ],
                        [
                            123.911301,
                            10.29619,
                            0
                        ],
                        [
                            123.91153,
                            10.2966,
                            0
                        ],
                        [
                            123.911613,
                            10.29673,
                            0
                        ],
                        [
                            123.911667,
                            10.29715,
                            0
                        ],
                        [
                            123.911667,
                            10.29747,
                            0
                        ],
                        [
                            123.911713,
                            10.29776,
                            0
                        ],
                        [
                            123.911797,
                            10.29804,
                            0
                        ],
                        [
                            123.911919,
                            10.29833,
                            0
                        ],
                        [
                            123.911972,
                            10.29864,
                            0
                        ],
                        [
                            123.912086,
                            10.29889,
                            0
                        ],
                        [
                            123.91227,
                            10.29913,
                            0
                        ],
                        [
                            123.912514,
                            10.29934,
                            0
                        ],
                        [
                            123.912773,
                            10.29953,
                            0
                        ],
                        [
                            123.91304,
                            10.29972,
                            0
                        ],
                        [
                            123.913193,
                            10.29979,
                            0
                        ],
                        [
                            123.91333,
                            10.29986,
                            0
                        ],
                        [
                            123.913643,
                            10.29998,
                            0
                        ],
                        [
                            123.913963,
                            10.30005,
                            0
                        ],
                        [
                            123.914268,
                            10.30024,
                            0
                        ],
                        [
                            123.91465,
                            10.30041,
                            0
                        ],
                        [
                            123.915024,
                            10.30071,
                            0
                        ],
                        [
                            123.915398,
                            10.301,
                            0
                        ],
                        [
                            123.915627,
                            10.30144,
                            0
                        ],
                        [
                            123.915863,
                            10.3018,
                            0
                        ],
                        [
                            123.916077,
                            10.30209,
                            0
                        ],
                        [
                            123.916267,
                            10.30238,
                            0
                        ],
                        [
                            123.916443,
                            10.30264,
                            0
                        ],
                        [
                            123.91658,
                            10.30274,
                            0
                        ],
                        [
                            123.91671,
                            10.30283,
                            0
                        ],
                        [
                            123.917007,
                            10.30306,
                            0
                        ],
                        [
                            123.917412,
                            10.30327,
                            0
                        ],
                        [
                            123.917747,
                            10.30331,
                            0
                        ],
                        [
                            123.918159,
                            10.30334,
                            0
                        ],
                        [
                            123.918404,
                            10.3037,
                            0
                        ],
                        [
                            123.918503,
                            10.30385,
                            0
                        ],
                        [
                            123.918633,
                            10.30406,
                            0
                        ],
                        [
                            123.919167,
                            10.30465,
                            0
                        ],
                        [
                            123.919662,
                            10.30516,
                            0
                        ],
                        [
                            123.920158,
                            10.30546,
                            0
                        ],
                        [
                            123.920532,
                            10.30558,
                            0
                        ],
                        [
                            123.920753,
                            10.30562,
                            0
                        ],
                        [
                            123.921089,
                            10.3056,
                            0
                        ],
                        [
                            123.921318,
                            10.30565,
                            0
                        ],
                        [
                            123.921608,
                            10.30583,
                            0
                        ],
                        [
                            123.921867,
                            10.306,
                            0
                        ],
                        [
                            123.922142,
                            10.30607,
                            0
                        ],
                        [
                            123.922447,
                            10.30665,
                            0
                        ],
                        [
                            123.922783,
                            10.30731,
                            0
                        ],
                        [
                            123.923157,
                            10.30776,
                            0
                        ],
                        [
                            123.923553,
                            10.30809,
                            0
                        ],
                        [
                            123.923927,
                            10.30837,
                            0
                        ],
                        [
                            123.924362,
                            10.30859,
                            0
                        ],
                        [
                            123.924881,
                            10.30879,
                            0
                        ],
                        [
                            123.92543,
                            10.30908,
                            0
                        ],
                        [
                            123.92585,
                            10.3095,
                            0
                        ],
                        [
                            123.926003,
                            10.30996,
                            0
                        ],
                        [
                            123.925827,
                            10.31039,
                            0
                        ],
                        [
                            123.925568,
                            10.31077,
                            0
                        ],
                        [
                            123.925423,
                            10.31092,
                            0
                        ],
                        [
                            123.925179,
                            10.31066,
                            0
                        ],
                        [
                            123.924713,
                            10.31016,
                            0
                        ],
                        [
                            123.924423,
                            10.30987,
                            0
                        ],
                        [
                            123.92421,
                            10.31014,
                            0
                        ],
                        [
                            123.924042,
                            10.31036,
                            0
                        ],
                        [
                            123.923531,
                            10.31116,
                            0
                        ],
                        [
                            123.923149,
                            10.31211,
                            0
                        ],
                        [
                            123.923286,
                            10.31263,
                            0
                        ],
                        [
                            123.923447,
                            10.31317,
                            0
                        ],
                        [
                            123.923851,
                            10.31407,
                            0
                        ],
                        [
                            123.924133,
                            10.31576,
                            0
                        ],
                        [
                            123.923958,
                            10.31714,
                            0
                        ],
                        [
                            123.92408,
                            10.31804,
                            0
                        ],
                        [
                            123.924171,
                            10.31922,
                            0
                        ],
                        [
                            123.924217,
                            10.31988,
                            0
                        ],
                        [
                            123.923729,
                            10.32172,
                            0
                        ],
                        [
                            123.923073,
                            10.32263,
                            0
                        ],
                        [
                            123.922691,
                            10.32395,
                            0
                        ],
                        [
                            123.922974,
                            10.32483,
                            0
                        ],
                        [
                            123.923149,
                            10.32552,
                            0
                        ],
                        [
                            123.923233,
                            10.32662,
                            0
                        ],
                        [
                            123.922997,
                            10.32777,
                            0
                        ],
                        [
                            123.922653,
                            10.3286,
                            0
                        ],
                        [
                            123.921349,
                            10.33046,
                            0
                        ],
                        [
                            123.92038,
                            10.33143,
                            0
                        ],
                        [
                            123.919342,
                            10.33283,
                            0
                        ],
                        [
                            123.918694,
                            10.33462,
                            0
                        ],
                        [
                            123.917427,
                            10.33576,
                            0
                        ],
                        [
                            123.916206,
                            10.3359,
                            0
                        ],
                        [
                            123.91851,
                            10.3466,
                            0
                        ],
                        [
                            123.919617,
                            10.35422,
                            0
                        ],
                        [
                            123.920158,
                            10.35758,
                            0
                        ],
                        [
                            123.921631,
                            10.36786,
                            0
                        ],
                        [
                            123.923363,
                            10.37682,
                            0
                        ],
                        [
                            123.924454,
                            10.38494,
                            0
                        ],
                        [
                            123.925858,
                            10.39706,
                            0
                        ],
                        [
                            123.925484,
                            10.39918,
                            0
                        ],
                        [
                            123.924896,
                            10.401,
                            0
                        ],
                        [
                            123.924454,
                            10.40299,
                            0
                        ],
                        [
                            123.924492,
                            10.40575,
                            0
                        ],
                        [
                            123.924789,
                            10.41434,
                            0
                        ],
                        [
                            123.925056,
                            10.41882,
                            0
                        ],
                        [
                            123.925377,
                            10.42824,
                            0
                        ],
                        [
                            123.9254,
                            10.43434,
                            0
                        ],
                        [
                            123.925697,
                            10.45163,
                            0
                        ],
                        [
                            123.92569,
                            10.45387,
                            0
                        ],
                        [
                            123.925667,
                            10.46187,
                            0
                        ],
                        [
                            123.925339,
                            10.46542,
                            0
                        ],
                        [
                            123.925827,
                            10.46973,
                            0
                        ],
                        [
                            123.926224,
                            10.47173,
                            0
                        ],
                        [
                            123.926033,
                            10.47292,
                            0
                        ],
                        [
                            123.92543,
                            10.47345,
                            0
                        ],
                        [
                            123.924919,
                            10.47372,
                            0
                        ],
                        [
                            123.92437,
                            10.47327,
                            0
                        ],
                        [
                            123.923576,
                            10.47261,
                            0
                        ],
                        [
                            123.922333,
                            10.47256,
                            0
                        ],
                        [
                            123.920837,
                            10.47319,
                            0
                        ],
                        [
                            123.92057,
                            10.47405,
                            0
                        ],
                        [
                            123.920532,
                            10.47485,
                            0
                        ],
                        [
                            123.920517,
                            10.4762,
                            0
                        ],
                        [
                            123.919403,
                            10.47897,
                            0
                        ],
                        [
                            123.918167,
                            10.48169,
                            0
                        ],
                        [
                            123.916946,
                            10.484,
                            0
                        ],
                        [
                            123.915932,
                            10.48465,
                            0
                        ],
                        [
                            123.914574,
                            10.48508,
                            0
                        ],
                        [
                            123.912514,
                            10.48561,
                            0
                        ],
                        [
                            123.910942,
                            10.48553,
                            0
                        ],
                        [
                            123.909363,
                            10.48566,
                            0
                        ],
                        [
                            123.906487,
                            10.48568,
                            0
                        ],
                        [
                            123.904182,
                            10.48609,
                            0
                        ],
                        [
                            123.901741,
                            10.48699,
                            0
                        ],
                        [
                            123.900124,
                            10.48789,
                            0
                        ],
                        [
                            123.898872,
                            10.48905,
                            0
                        ],
                        [
                            123.897583,
                            10.4901,
                            0
                        ],
                        [
                            123.896172,
                            10.49079,
                            0
                        ],
                        [
                            123.89547,
                            10.49077,
                            0
                        ],
                        [
                            123.89447,
                            10.49021,
                            0
                        ],
                        [
                            123.89325,
                            10.48948,
                            0
                        ],
                        [
                            123.892693,
                            10.48941,
                            0
                        ],
                        [
                            123.89183,
                            10.48984,
                            0
                        ]
                    ]
                ]
            },
            "properties": {
                "name": "Cebu City",
                "styleUrl": "#poly-DF0000-3001-0",
                "styleHash": "-436e1d8b",
                "styleMapHash": {
                    "normal": "#poly-DF0000-3001-0-normal",
                    "highlight": "#poly-DF0000-3001-0-highlight"
                },
                "description": "Lungsod|Siyudad",
                "stroke": "#df0000",
                "stroke-opacity": 1,
                "stroke-width": 3.001,
                "fill": "#df0000",
                "fill-opacity": 1
            }
        }
    ]
}